whatxtract/__init__.py
whatxtract/__main__.py
whatxtract/adb_controller.py
whatxtract/constants.py
whatxtract/db_parser.py
whatxtract/logging_setup.py
whatxtract/test.py
whatxtract/utils.py
whatxtract/wa_emulator.py
whatxtract/waweb.py
whatxtract-1.0.8.dist-info/METADATA
whatxtract-1.0.8.dist-info/WHEEL
whatxtract-1.0.8.dist-info/entry_points.txt
whatxtract-1.0.8.dist-info/licenses/LICENSE
whatxtract-1.0.8.dist-info/RECORD
