Metadata-Version: 2.4
Name: whatxtract
Version: 1.0.8
Summary: Extract and verify WhatsApp contact numbers via WhatsApp Web using an automation-powered Python toolkit.
Project-URL: Homepage, https://github.com/bitbytelab/whatxtract
Project-URL: Issues, https://github.com/bitbytelab/whatxtract/issues
Author-email: Hasan Rasel <rrss.mahmud@gmail.com>
License-Expression: MIT
License-File: LICENSE
Keywords: Contacts Extractor,WhatsApp,WhatsApp Automation,WhatsApp Extractor,WhatsApp Number Checker,WhatsApp User Checker,WhatsApp Validator,WhatsApp Web Scraper
Classifier: Development Status :: 3 - Alpha
Classifier: Intended Audience :: Developers
Classifier: Operating System :: OS Independent
Classifier: Programming Language :: Python :: 3.10
Classifier: Programming Language :: Python :: 3.11
Classifier: Topic :: Communications :: Chat
Classifier: Topic :: Communications :: Telephony
Classifier: Topic :: Internet :: WWW/HTTP :: Browsers
Classifier: Topic :: Software Development :: Libraries :: Python Modules
Requires-Python: >=3.10
Requires-Dist: colorlog
Requires-Dist: faker
Requires-Dist: selenium
Requires-Dist: tqdm
Requires-Dist: undetected-chromedriver
Provides-Extra: dev
Requires-Dist: hatchling; extra == 'dev'
Requires-Dist: uv-dynamic-versioning; extra == 'dev'
